scenvi/ENVI.py
scenvi/__init__.py
scenvi/_dists.py
scenvi/utils.py
scenvi-0.4.6.dist-info/LICENSE
scenvi-0.4.6.dist-info/METADATA
scenvi-0.4.6.dist-info/WHEEL
scenvi-0.4.6.dist-info/RECORD
