Metadata-Version: 2.1
Name: scenvi
Version: 0.4.6
Summary: Integration of scRNA-seq and spatial transcpriptomics data
License: MIT
Author: Doron Haviv
Requires-Python: >=3.9,<4.0
Classifier: License :: OSI Approved :: MIT License
Classifier: Programming Language :: Python :: 3
Classifier: Programming Language :: Python :: 3.9
Classifier: Programming Language :: Python :: 3.10
Classifier: Programming Language :: Python :: 3.11
Requires-Dist: clu (>=0.0.11,<0.0.12)
Requires-Dist: flax (>=0.10.4,<0.11.0)
Requires-Dist: optax (>=0.2.4,<0.3.0)
Requires-Dist: scanpy (>=1.11.0,<2.0.0)
Requires-Dist: tensorflow_probability (>=0.22.0,<0.23.0)
Requires-Dist: tqdm (>=4.66.1,<5.0.0)
